{
  "version": "7",
  "dialect": "postgresql",
  "entries": [
    {
      "idx": 0,
      "version": "7",
      "when": 1723989644947,
      "tag": "0000_slimy_christian_walker",
      "breakpoints": true
    },
    {
      "idx": 1,
      "version": "7",
      "when": 1724009770223,
      "tag": "0001_material_cardiac",
      "breakpoints": true
    },
    {
      "idx": 2,
      "version": "7",
      "when": 1724069223864,
      "tag": "0002_cynical_living_mummy",
      "breakpoints": true
    },
    {
      "idx": 3,
      "version": "7",
      "when": 1724085218006,
      "tag": "0003_dazzling_logan",
      "breakpoints": true
    },
    {
      "idx": 4,
      "version": "7",
      "when": 1724087005102,
      "tag": "0004_confused_lord_hawal",
      "breakpoints": true
    },
    {
      "idx": 5,
      "version": "7",
      "when": 1724093270582,
      "tag": "0005_sloppy_jubilee",
      "breakpoints": true
    },
    {
      "idx": 6,
      "version": "7",
      "when": 1724674508696,
      "tag": "0006_silly_shinko_yamashiro",
      "breakpoints": true
    },
    {
      "idx": 7,
      "version": "7",
      "when": 1724939515407,
      "tag": "0007_gigantic_rictor",
      "breakpoints": true
    },
    {
      "idx": 8,
      "version": "7",
      "when": 1724939624911,
      "tag": "0008_open_speedball",
      "breakpoints": true
    },
    {
      "idx": 9,
      "version": "7",
      "when": 1724952633636,
      "tag": "0009_bored_the_order",
      "breakpoints": true
    },
    {
      "idx": 10,
      "version": "7",
      "when": 1725038857415,
      "tag": "0010_organic_bulldozer",
      "breakpoints": true
    },
    {
      "idx": 11,
      "version": "7",
      "when": 1725200973553,
      "tag": "0011_chilly_the_captain",
      "breakpoints": true
    },
    {
      "idx": 12,
      "version": "7",
      "when": 1725781057929,
      "tag": "0012_conscious_mole_man",
      "breakpoints": true
    },
    {
      "idx": 13,
      "version": "7",
      "when": 1725960054501,
      "tag": "0013_ordinary_king_cobra",
      "breakpoints": true
    },
    {
      "idx": 14,
      "version": "7",
      "when": 1725978156173,
      "tag": "0014_clumsy_franklin_storm",
      "breakpoints": true
    },
    {
      "idx": 15,
      "version": "7",
      "when": 1725978354018,
      "tag": "0015_glossy_snowbird",
      "breakpoints": true
    },
    {
      "idx": 16,
      "version": "7",
      "when": 1726557153270,
      "tag": "0016_brown_lenny_balinger",
      "breakpoints": true
    },
    {
      "idx": 17,
      "version": "7",
      "when": 1726564296306,
      "tag": "0017_thin_sharon_ventura",
      "breakpoints": true
    },
    {
      "idx": 18,
      "version": "7",
      "when": 1726564475961,
      "tag": "0018_fluffy_blade",
      "breakpoints": true
    },
    {
      "idx": 19,
      "version": "7",
      "when": 1726594662505,
      "tag": "0019_lucky_the_watchers",
      "breakpoints": true
    },
    {
      "idx": 20,
      "version": "7",
      "when": 1726661345557,
      "tag": "0020_regular_sebastian_shaw",
      "breakpoints": true
    },
    {
      "idx": 21,
      "version": "7",
      "when": 1726663945585,
      "tag": "0021_cooing_sersi",
      "breakpoints": true
    },
    {
      "idx": 22,
      "version": "7",
      "when": 1726682285661,
      "tag": "0022_early_riptide",
      "breakpoints": true
    },
    {
      "idx": 23,
      "version": "7",
      "when": 1726757225159,
      "tag": "0023_noisy_moira_mactaggert",
      "breakpoints": true
    }
  ]
}